spi_slave.v
module spi_slave(
    input clk,      // Clock input
    input rst,      // Reset input
    input ss,       // Slave Select
    input mosi,     // Master Out, Slave In
    output miso,    // Master In, Slave Out
    input sck,      // Serial Clock
    output done,    // Data transmission done flag
    input [7:0] din,  // 8-bit data input
    output [7:0] dout // 8-bit data output
);

// Declare registers for internal operations
reg mosi_d, mosi_q;
reg ss_d, ss_q;
reg sck_d, sck_q;
reg sck_old_d, sck_old_q;
  reg [7:0] data_d, data_q;
reg done_d, done_q;
reg [2:0] bit_ct_d, bit_ct_q; // Bit counter, 3 bits to count 0-7
reg [7:0] dout_d, dout_q;
reg miso_d, miso_q;

// Assigning register values to output
assign miso = miso_q;
assign done = done_q;
assign dout = dout_q;

// Combinational Logic Block
always @(*) begin
    // Default assignments for combinational variables
    ss_d      = ss;
    mosi_d    = mosi;
    miso_d    = miso_q;
    sck_d     = sck;
    sck_old_d = sck_q;
    data_d    = data_q;
    done_d    = 1'b0; // Ensure done flag is low by default
    bit_ct_d  = bit_ct_q;
    dout_d    = dout_q;

    // Check if slave is selected (ss is low when selected)
    if (ss_q) begin
        bit_ct_d = 3'b0;  // Reset bit counter
        data_d   = din;   // Load new data to be transmitted
        miso_d   = data_q[7]; // Assign most significant bit to miso
    end else begin
        // On Rising edge of Serial Clock (sck)
        if (!sck_old_q && sck_q) begin 
            data_d   = {data_q[6:0], mosi_q}; // Shift in mosi bit
            bit_ct_d = bit_ct_q + 1'b1;       // Increment bit count

            // If 8 bits have been processed
            if (bit_ct_q == 3'b111) begin
                dout_d = {data_q[6:0], mosi_q}; // Update dout with received byte
                done_d = 1'b1; // Set done flag high indicating byte reception is complete
                data_d = din;  // Load new data to be transmitted next
            end
        // On Falling edge of Serial Clock (sck)
        end else if (sck_old_q && !sck_q) begin 
            miso_d = data_q[7]; // Assign most significant bit to miso
        end
    end
end

// Sequential Logic Block
always @(posedge clk) begin
    // Check if reset is active
    if (rst) begin
        // Reset all sequential variables
        done_q  <= 1'b0;
        bit_ct_q <= 3'b0;
        dout_q  <= 8'b0;
        miso_q  <= 1'b1;
    end else begin
        // Transfer values from combinational (_d) to sequential (_q) variables
        done_q <= done_d;
        bit_ct_q <= bit_ct_d;
        dout_q <= dout_d;
        miso_q <= miso_d;
    end
    
    // Update old state registers with current state values
    sck_q <= sck_d;
    mosi_q <= mosi_d;
    ss_q <= ss_d;
    data_q <= data_d;
    sck_old_q <= sck_old_d;
end

endmodule

spi_master.v
module spi_master #(
    parameter CLK_DIV = 2   // Clock division factor
)(
    input clk,        // Clock input
    input rst,        // Reset input
    input miso,       // Master In Slave Out data line
    output mosi,      // Master Out Slave In data line
    output sck,       // Serial Clock line
    input start,      // Start signal
    input [7:0] data_in, // 8-bit input data
    output [7:0] data_out, // 8-bit output data
    output busy,      // Busy flag
    output new_data   // New data available flag
);

    // State definitions
    localparam STATE_SIZE = 2;
    localparam IDLE = 2'd0,
               WAIT_HALF = 2'd1,
               TRANSFER = 2'd2;

    // Internal registers
    reg [STATE_SIZE-1:0] state_d, state_q;
    reg [7:0] data_d, data_q;
    reg [CLK_DIV-1:0] sck_d, sck_q;
    reg mosi_d, mosi_q;
    reg [2:0] ctr_d, ctr_q;
    reg new_data_d, new_data_q;
    reg [7:0] data_out_d, data_out_q;

    // Output assignments
    assign mosi = mosi_d; //pragya changed from mosi_q to mosi_d
    assign sck = (~sck_q[CLK_DIV-1]) & (state_q == TRANSFER);
    assign busy = state_q != IDLE;
    assign data_out = data_out_q;
    assign new_data = new_data_q;

    // Combinational Logic Block
    always @(*) begin
        // Default assignments
        sck_d = sck_q;
        data_d = data_q;
        mosi_d = mosi_q;
        ctr_d = ctr_q;
        new_data_d = 1'b0;
        data_out_d = data_out_q;
        state_d = state_q;

        // State machine
        case (state_q)
            IDLE: begin
                sck_d = 4'b0;  // Reset clock counter
                ctr_d = 3'b0;  // Reset bit counter
                // If start signal is active
                if (start == 1'b1) begin
                    data_d = data_in; // Load input data
                    state_d = WAIT_HALF; // Move to next state
                end
            end

            WAIT_HALF: begin
                sck_d = sck_q + 1'b1;  // Increment clock counter
                // If half of the clock period has elapsed
                if (sck_q == {CLK_DIV-1{1'b1}}) begin
                    sck_d = 1'b0;  // Reset clock counter
                    state_d = TRANSFER; // Move to next state
                end
            end

            TRANSFER: begin
                sck_d = sck_q + 1'b1;  // Increment clock counter
                // If the clock counter is at zero (rising edge)
                if (sck_q == 4'b0000) begin
                    mosi_d = data_q[7];  // Set the most significant bit to mosi
                // If the clock is half full (falling edge)
                end else if (sck_q == {CLK_DIV-1{1'b1}}) begin
                    data_d = {data_q[6:0], miso};  // Shift and include miso bit
                // If clock counter is full (rising edge)
                end else if (sck_q == {CLK_DIV{1'b1}}) begin
                    ctr_d = ctr_q + 1'b1;  // Increment bit counter
                    // If we are on the last bit
                    if (ctr_q == 3'b111) begin
                        state_d = IDLE;  // Go back to idle state
                        data_out_d = data_q; // Set the output data register
                        new_data_d = 1'b1; // Indicate new data is available
                    end
                end
            end
        endcase
    end

    // Sequential Logic Block
    always @(posedge clk) begin
        if (rst) begin
            // On reset, initialize all registers
            ctr_q <= 3'b0;
            data_q <= 8'b0;
            sck_q <= 4'b0;
            mosi_q <= 1'b0;
            state_q <= IDLE;
            data_out_q <= 8'b0;
            new_data_q <= 1'b0;
        end else begin
            // Transfer intermediate values to state registers
            ctr_q <= ctr_d;
            data_q <= data_d;
            sck_q <= sck_d;
            mosi_q <= mosi_d;
            state_q <= state_d;
            data_out_q <= data_out_d;
            new_data_q <= new_data_d;
        end
    end
endmodule

spi_tb.v
module spi_tb;
  reg[7:0] in_slave_data, in_master_data;
  reg clk, reset;
  wire[7:0] out_slave_data, out_master_data;
  wire new_data, mosi, miso, sck, slave_done;
  integer i;
  reg ss, start;
  spi_master spi_m(.clk(clk),       
                   .rst(reset),       
                   .miso(miso),       
                   .mosi(mosi),     
                   .sck(sck),     
                   .start(start),     
                   .data_in(in_master_data), 
                   .data_out(out_master_data), 
                   .busy(),     
                   .new_data(new_data));
  spi_slave spi_s(.clk(clk),     
                  .rst(reset),    
                  .ss(ss),    
                  .mosi(mosi),  
                  .miso(miso),  
                  .sck(sck),    
                  .done(slave_done), 
                  .din(in_slave_data),  
                  .dout(out_slave_data));
  
  always #2 clk = ~clk;
  
  always @(posedge slave_done) begin //{
    in_master_data = in_master_data + 3'h3;
    in_slave_data = in_slave_data +4'h8;
  end //}
  
  initial begin
    clk = 1'b0; reset = 1'b0; ss = 1'b1; start = 1'b0; 
    in_slave_data= 8'h0;
    in_master_data = 8'h0;
    
    #3 reset = 1'b1;
    #4 reset = 1'b0;
    #10;
    #1 in_master_data = 8'h1c;
    in_slave_data = 8'hc1;
    #50;
    ss = 1'b0;
    start = 1'b1;
    $monitor("Sim time %t, in_master_data %h, new_master_data %b, out_slave_data %h, slave_done %b, in_slave data %h, out_master_data %h", $time,in_master_data,new_data,out_slave_data,slave_done,in_slave_data, out_master_data);
    #1000 $finish;
  end
  
  
  
  initial begin
    $dumpfile("dump.vcd");
   $dumpvars;
  end    
endmodule

dump.vcd
$date
	Fri Oct 20 10:36:02 2023
$end
$version
	Icarus Verilog
$end
$timescale
	1s
$end
$scope module spi_tb $end
$var wire 1 ! slave_done $end
$var wire 1 " sck $end
$var wire 8 # out_slave_data [7:0] $end
$var wire 8 $ out_master_data [7:0] $end
$var wire 1 % new_data $end
$var wire 1 & mosi $end
$var wire 1 ' miso $end
$var reg 1 ( clk $end
$var reg 8 ) in_master_data [7:0] $end
$var reg 8 * in_slave_data [7:0] $end
$var reg 1 + reset $end
$var reg 1 , ss $end
$var reg 1 - start $end
$scope module spi_m $end
$var wire 1 ( clk $end
$var wire 8 . data_in [7:0] $end
$var wire 8 / data_out [7:0] $end
$var wire 1 & mosi $end
$var wire 1 % new_data $end
$var wire 1 + rst $end
$var wire 1 " sck $end
$var wire 1 - start $end
$var wire 1 ' miso $end
$var wire 1 0 busy $end
$var reg 3 1 ctr_d [2:0] $end
$var reg 3 2 ctr_q [2:0] $end
$var reg 8 3 data_d [7:0] $end
$var reg 8 4 data_out_d [7:0] $end
$var reg 8 5 data_out_q [7:0] $end
$var reg 8 6 data_q [7:0] $end
$var reg 1 7 mosi_d $end
$var reg 1 8 mosi_q $end
$var reg 1 9 new_data_d $end
$var reg 1 : new_data_q $end
$var reg 2 ; sck_d [1:0] $end
$var reg 2 < sck_q [1:0] $end
$var reg 2 = state_d [1:0] $end
$var reg 2 > state_q [1:0] $end
$upscope $end
$scope module spi_s $end
$var wire 1 ( clk $end
$var wire 8 ? din [7:0] $end
$var wire 1 ! done $end
$var wire 8 @ dout [7:0] $end
$var wire 1 ' miso $end
$var wire 1 & mosi $end
$var wire 1 + rst $end
$var wire 1 " sck $end
$var wire 1 , ss $end
$var reg 3 A bit_ct_d [2:0] $end
$var reg 3 B bit_ct_q [2:0] $end
$var reg 8 C data_d [7:0] $end
$var reg 8 D data_q [7:0] $end
$var reg 1 E done_d $end
$var reg 1 F done_q $end
$var reg 8 G dout_d [7:0] $end
$var reg 8 H dout_q [7:0] $end
$var reg 1 I miso_d $end
$var reg 1 J miso_q $end
$var reg 1 K mosi_d $end
$var reg 1 L mosi_q $end
$var reg 1 M sck_d $end
$var reg 1 N sck_old_d $end
$var reg 1 O sck_old_q $end
$var reg 1 P sck_q $end
$var reg 1 Q ss_d $end
$var reg 1 R ss_q $end
$upscope $end
$upscope $end
$enddefinitions $end
#0
$dumpvars
xR
1Q
xP
xO
xN
xM
xL
xK
xJ
xI
bx H
bx G
xF
0E
bx D
bx C
bx B
bx A
bx @
b0 ?
bx >
bx =
bx <
bx ;
x:
09
x8
x7
bx 6
bx 5
bx 4
bx 3
bx 2
bx 1
x0
bx /
b0 .
0-
1,
0+
b0 *
b0 )
0(
x'
x&
x%
bx $
bx #
x"
x!
$end
#2
b0 C
b0 A
0%
0:
1R
0!
0F
1(
#3
1+
#4
0(
#6
b0 G
0M
0I
0K
0"
b0 =
b0 4
b0 1
0&
07
b0 3
b0 ;
b0 D
1'
1J
b0 #
b0 @
b0 H
b0 B
b0 $
b0 /
b0 5
00
b0 >
08
b0 <
b0 6
b0 2
1(
#7
0+
#8
0(
#10
0N
0L
0P
0'
0J
1(
#12
0(
#14
0O
1(
#16
0(
#18
b11000001 C
b11000001 *
b11000001 ?
b11100 )
b11100 .
1(
#20
0(
#22
1I
b11000001 D
1(
#24
0(
#26
1'
1J
1(
#28
0(
#30
1(
#32
0(
#34
1(
#36
0(
#38
1(
#40
0(
#42
1(
#44
0(
#46
1(
#48
0(
#50
1(
#52
0(
#54
1(
#56
0(
#58
1(
#60
0(
#62
1(
#64
0(
#66
1(
#68
b1 =
b11100 3
0Q
0(
1-
0,
#70
b1 ;
0R
10
b1 >
b11100 6
1(
#72
0(
#74
b10 =
b0 ;
b1 <
1(
#76
0(
#78
1M
1"
b1 ;
b10 >
b0 <
1(
#80
0(
#82
b111001 3
b10 ;
b1 A
b10000010 C
1N
b1 <
1P
1(
#84
0(
#86
0M
0"
b11 ;
1O
b10000010 D
b1 B
b10 <
b111001 6
1(
#88
0(
#90
b1 1
b0 ;
0N
b11 <
0P
1(
#92
0(
#94
1M
1"
b1 ;
0O
b0 <
b1 2
1(
#96
0(
#98
b1110011 3
b10 ;
b10 A
b100 C
1N
b1 <
1P
1(
#100
0(
#102
0M
0"
b11 ;
1O
b100 D
b10 B
b10 <
b1110011 6
1(
#104
0(
#106
b10 1
b0 ;
0I
0N
b11 <
0P
1(
#108
0(
#110
1M
1"
b1 ;
0O
0'
0J
b0 <
b10 2
1(
#112
0(
#114
b11100110 3
b10 ;
b11 A
b1000 C
1N
b1 <
1P
1(
#116
0(
#118
0M
0"
b11 ;
1O
b1000 D
b11 B
b10 <
b11100110 6
1(
#120
0(
#122
b11 1
b0 ;
0N
b11 <
0P
1(
#124
0(
#126
1M
1"
1K
1&
17
b1 ;
0O
b0 <
b11 2
1(
#128
0(
#130
b11001100 3
b10 ;
b100 A
b10001 C
1N
18
b1 <
1L
1P
1(
#132
0(
#134
0M
0"
b11 ;
1O
b10001 D
b100 B
b10 <
b11001100 6
1(
#136
0(
#138
b100 1
b0 ;
0N
b11 <
0P
1(
#140
0(
#142
1M
1"
b1 ;
0O
b0 <
b100 2
1(
#144
0(
#146
b10011000 3
b10 ;
b101 A
b100011 C
1N
b1 <
1P
1(
#148
0(
#150
0M
0"
b11 ;
1O
b100011 D
b101 B
b10 <
b10011000 6
1(
#152
0(
#154
b101 1
b0 ;
0N
b11 <
0P
1(
#156
0(
#158
1M
1"
b1 ;
0O
b0 <
b101 2
1(
#160
0(
#162
b110000 3
b10 ;
b110 A
b1000111 C
1N
b1 <
1P
1(
#164
0(
#166
0M
0"
b11 ;
1O
b1000111 D
b110 B
b10 <
b110000 6
1(
#168
0(
#170
b110 1
b0 ;
0N
b11 <
0P
1(
#172
0(
#174
1M
1"
0K
0&
07
b1 ;
0O
b0 <
b110 2
1(
#176
0(
#178
b1100000 3
b10 ;
b111 A
b10001110 C
1N
08
b1 <
0L
1P
1(
#180
0(
#182
0M
0"
b11 ;
1O
b10001110 D
b111 B
b10 <
b1100000 6
1(
#184
0(
#186
b111 1
b0 ;
1I
0N
b11 <
0P
1(
#188
0(
#190
1M
1"
b1 ;
0O
1'
1J
b0 <
b111 2
1(
#192
0(
#194
b11000001 3
b10 ;
1E
b11100 G
b0 A
b11000001 C
1N
b1 <
1P
1(
#196
0(
#198
0M
0"
0E
b11001001 *
b11001001 ?
b11111 )
b11111 .
b11 ;
1O
b11000001 D
b11100 #
b11100 @
b11100 H
b0 B
1!
1F
b10 <
b11000001 6
1(
#200
0(
#202
19
b11000001 4
b0 =
b0 1
b0 ;
0N
b11 <
0P
0!
0F
1(
#204
0(
#206
b1 =
b11111 3
09
0O
1%
1:
b11000001 $
b11000001 /
b11000001 5
00
b0 >
b0 <
b0 2
1(
#208
0(
#210
b1 ;
0%
0:
10
b1 >
b11111 6
1(
#212
0(
#214
b10 =
b0 ;
b1 <
1(
#216
0(
#218
1M
1"
b1 ;
b10 >
b0 <
1(
#220
0(
#222
b1 A
b10000010 C
1N
b111111 3
b10 ;
1P
b1 <
1(
#224
0(
#226
0M
0"
b11 ;
b10 <
b111111 6
1O
b10000010 D
b1 B
1(
#228
0(
#230
0N
b1 1
b0 ;
0P
b11 <
1(
#232
0(
#234
1M
1"
b1 ;
b0 <
b1 2
0O
1(
#236
0(
#238
b10 A
b100 C
1N
b1111111 3
b10 ;
1P
b1 <
1(
#240
0(
#242
0M
0"
b11 ;
b10 <
b1111111 6
1O
b100 D
b10 B
1(
#244
0(
#246
0I
0N
b10 1
b0 ;
0P
b11 <
1(
#248
0(
#250
1M
1"
b1 ;
b0 <
b10 2
0O
0'
0J
1(
#252
0(
#254
b11 A
b1000 C
1N
b11111110 3
b10 ;
1P
b1 <
1(
#256
0(
#258
0M
0"
b11 ;
b10 <
b11111110 6
1O
b1000 D
b11 B
1(
#260
0(
#262
0N
b11 1
b0 ;
0P
b11 <
1(
#264
0(
#266
1M
1"
1K
1&
17
b1 ;
b0 <
b11 2
0O
1(
#268
0(
#270
b100 A
b10001 C
1N
b11111100 3
b10 ;
1L
1P
18
b1 <
1(
#272
0(
#274
0M
0"
b11 ;
b10 <
b11111100 6
1O
b10001 D
b100 B
1(
#276
0(
#278
0N
b100 1
b0 ;
0P
b11 <
1(
#280
0(
#282
1M
1"
b1 ;
b0 <
b100 2
0O
1(
#284
0(
#286
b101 A
b100011 C
1N
b11111000 3
b10 ;
1P
b1 <
1(
#288
0(
#290
0M
0"
b11 ;
b10 <
b11111000 6
1O
b100011 D
b101 B
1(
#292
0(
#294
0N
b101 1
b0 ;
0P
b11 <
1(
#296
0(
#298
1M
1"
b1 ;
b0 <
b101 2
0O
1(
#300
0(
#302
b110 A
b1000111 C
1N
b11110000 3
b10 ;
1P
b1 <
1(
#304
0(
#306
0M
0"
b11 ;
b10 <
b11110000 6
1O
b1000111 D
b110 B
1(
#308
0(
#310
0N
b110 1
b0 ;
0P
b11 <
1(
#312
0(
#314
1M
1"
b1 ;
b0 <
b110 2
0O
1(
#316
0(
#318
b111 A
b10001111 C
1N
b11100000 3
b10 ;
1P
b1 <
1(
#320
0(
#322
0M
0"
b11 ;
b10 <
b11100000 6
1O
b10001111 D
b111 B
1(
#324
0(
#326
1I
0N
b111 1
b0 ;
0P
b11 <
1(
#328
0(
#330
1M
1"
b1 ;
b0 <
b111 2
0O
1'
1J
1(
#332
0(
#334
1E
b11111 G
b0 A
b11001001 C
1N
b11000001 3
b10 ;
1P
b1 <
1(
#336
0(
#338
0M
0"
b11 ;
0E
b11010001 *
b11010001 ?
b100010 )
b100010 .
b10 <
b11000001 6
1O
b11001001 D
b11111 #
b11111 @
b11111 H
b0 B
1!
1F
1(
#340
0(
#342
0N
19
b0 =
b0 1
b0 ;
0P
0!
0F
b11 <
1(
#344
0(
#346
b1 =
b100010 3
09
1%
1:
00
b0 >
b0 <
b0 2
0O
1(
#348
0(
#350
b1 ;
0%
0:
10
b1 >
b100010 6
1(
#352
0(
#354
b10 =
b0 ;
b1 <
1(
#356
0(
#358
1M
0K
1"
0&
07
b1 ;
b10 >
b0 <
1(
#360
0(
#362
b1000101 3
b10 ;
b1 A
b10010010 C
1N
08
b1 <
0L
1P
1(
#364
0(
#366
0M
0"
b11 ;
1O
b10010010 D
b1 B
b10 <
b1000101 6
1(
#368
0(
#370
b1 1
b0 ;
0N
b11 <
0P
1(
#372
0(
#374
1M
1"
b1 ;
0O
b0 <
b1 2
1(
#376
0(
#378
b10001011 3
b10 ;
b10 A
b100100 C
1N
b1 <
1P
1(
#380
0(
#382
0M
0"
b11 ;
1O
b100100 D
b10 B
b10 <
b10001011 6
1(
#384
0(
#386
b10 1
b0 ;
0I
0N
b11 <
0P
1(
#388
0(
#390
1M
1"
1K
1&
17
b1 ;
0O
0'
0J
b0 <
b10 2
1(
#392
0(
#394
b10110 3
b10 ;
b11 A
b1001001 C
1N
18
b1 <
1L
1P
1(
#396
0(
#398
0M
0"
b11 ;
1O
b1001001 D
b11 B
b10 <
b10110 6
1(
#400
0(
#402
b11 1
b0 ;
0N
b11 <
0P
1(
#404
0(
#406
1M
1"
0K
0&
07
b1 ;
0O
b0 <
b11 2
1(
#408
0(
#410
b101100 3
b10 ;
b100 A
b10010010 C
1N
08
b1 <
0L
1P
1(
#412
0(
#414
0M
0"
b11 ;
1O
b10010010 D
b100 B
b10 <
b101100 6
1(
#416
0(
#418
b100 1
b0 ;
1I
0N
b11 <
0P
1(
#420
0(
#422
1M
1"
b1 ;
0O
1'
1J
b0 <
b100 2
1(
#424
0(
#426
b1011001 3
b10 ;
b101 A
b100100 C
1N
b1 <
1P
1(
#428
0(
#430
0M
0"
b11 ;
1O
b100100 D
b101 B
b10 <
b1011001 6
1(
#432
0(
#434
b101 1
b0 ;
0I
0N
b11 <
0P
1(
#436
0(
#438
1M
1"
b1 ;
0O
0'
0J
b0 <
b101 2
1(
#440
0(
#442
b10110010 3
b10 ;
b110 A
b1001000 C
1N
b1 <
1P
1(
#444
0(
#446
0M
0"
b11 ;
1O
b1001000 D
b110 B
b10 <
b10110010 6
1(
#448
0(
#450
b110 1
b0 ;
0N
b11 <
0P
1(
#452
0(
#454
1M
1"
1K
1&
17
b1 ;
0O
b0 <
b110 2
1(
#456
0(
#458
b1100100 3
b10 ;
b111 A
b10010001 C
1N
18
b1 <
1L
1P
1(
#460
0(
#462
0M
0"
b11 ;
1O
b10010001 D
b111 B
b10 <
b1100100 6
1(
#464
0(
#466
b111 1
b0 ;
1I
0N
b11 <
0P
1(
#468
0(
#470
1M
1"
0K
0&
07
b1 ;
0O
1'
1J
b0 <
b111 2
1(
#472
0(
#474
b11001001 3
b10 ;
1E
b100010 G
b0 A
b11010001 C
1N
08
b1 <
0L
1P
1(
#476
0(
#478
0M
0"
0E
b11011001 *
b11011001 ?
b100101 )
b100101 .
b11 ;
1O
b11010001 D
b100010 #
b100010 @
b100010 H
b0 B
1!
1F
b10 <
b11001001 6
1(
#480
0(
#482
19
b11001001 4
b0 =
b0 1
b0 ;
0N
b11 <
0P
0!
0F
1(
#484
0(
#486
b1 =
b100101 3
09
0O
1%
1:
b11001001 $
b11001001 /
b11001001 5
00
b0 >
b0 <
b0 2
1(
#488
0(
#490
b1 ;
0%
0:
10
b1 >
b100101 6
1(
#492
0(
#494
b10 =
b0 ;
b1 <
1(
#496
0(
#498
1M
1"
b1 ;
b10 >
b0 <
1(
#500
0(
#502
b1 A
b10100010 C
1N
b1001011 3
b10 ;
1P
b1 <
1(
#504
0(
#506
0M
0"
b11 ;
b10 <
b1001011 6
1O
b10100010 D
b1 B
1(
#508
0(
#510
0N
b1 1
b0 ;
0P
b11 <
1(
#512
0(
#514
1M
1"
b1 ;
b0 <
b1 2
0O
1(
#516
0(
#518
b10 A
b1000100 C
1N
b10010111 3
b10 ;
1P
b1 <
1(
#520
0(
#522
0M
0"
b11 ;
b10 <
b10010111 6
1O
b1000100 D
b10 B
1(
#524
0(
#526
0I
0N
b10 1
b0 ;
0P
b11 <
1(
#528
0(
#530
1M
1"
1K
1&
17
b1 ;
b0 <
b10 2
0O
0'
0J
1(
#532
0(
#534
b11 A
b10001001 C
1N
b101110 3
b10 ;
1L
1P
18
b1 <
1(
#536
0(
#538
0M
0"
b11 ;
b10 <
b101110 6
1O
b10001001 D
b11 B
1(
#540
0(
#542
1I
0N
b11 1
b0 ;
0P
b11 <
1(
#544
0(
#546
1M
1"
0K
0&
07
b1 ;
b0 <
b11 2
0O
1'
1J
1(
#548
0(
#550
b100 A
b10010 C
1N
b1011101 3
b10 ;
0L
1P
08
b1 <
1(
#552
0(
#554
0M
0"
b11 ;
b10 <
b1011101 6
1O
b10010 D
b100 B
1(
#556
0(
#558
0I
0N
b100 1
b0 ;
0P
b11 <
1(
#560
0(
#562
1M
1"
b1 ;
b0 <
b100 2
0O
0'
0J
1(
#564
0(
#566
b101 A
b100100 C
1N
b10111010 3
b10 ;
1P
b1 <
1(
#568
0(
#570
0M
0"
b11 ;
b10 <
b10111010 6
1O
b100100 D
b101 B
1(
#572
0(
#574
0N
b101 1
b0 ;
0P
b11 <
1(
#576
0(
#578
1M
1"
1K
1&
17
b1 ;
b0 <
b101 2
0O
1(
#580
0(
#582
b110 A
b1001001 C
1N
b1110100 3
b10 ;
1L
1P
18
b1 <
1(
#584
0(
#586
0M
0"
b11 ;
b10 <
b1110100 6
1O
b1001001 D
b110 B
1(
#588
0(
#590
0N
b110 1
b0 ;
0P
b11 <
1(
#592
0(
#594
1M
1"
0K
0&
07
b1 ;
b0 <
b110 2
0O
1(
#596
0(
#598
b111 A
b10010010 C
1N
b11101000 3
b10 ;
0L
1P
08
b1 <
1(
#600
0(
#602
0M
0"
b11 ;
b10 <
b11101000 6
1O
b10010010 D
b111 B
1(
#604
0(
#606
1I
0N
b111 1
b0 ;
0P
b11 <
1(
#608
0(
#610
1M
1"
1K
1&
17
b1 ;
b0 <
b111 2
0O
1'
1J
1(
#612
0(
#614
1E
b100101 G
b0 A
b11011001 C
1N
b11010001 3
b10 ;
1L
1P
18
b1 <
1(
#616
0(
#618
0M
0"
b11 ;
0E
b11100001 *
b11100001 ?
b101000 )
b101000 .
b10 <
b11010001 6
1O
b11011001 D
b100101 #
b100101 @
b100101 H
b0 B
1!
1F
1(
#620
0(
#622
0N
19
b11010001 4
b0 =
b0 1
b0 ;
0P
0!
0F
b11 <
1(
#624
0(
#626
b1 =
b101000 3
09
1%
1:
b11010001 $
b11010001 /
b11010001 5
00
b0 >
b0 <
b0 2
0O
1(
#628
0(
#630
b1 ;
0%
0:
10
b1 >
b101000 6
1(
#632
0(
#634
b10 =
b0 ;
b1 <
1(
#636
0(
#638
1M
0K
1"
0&
07
b1 ;
b10 >
b0 <
1(
#640
0(
#642
b1010001 3
b10 ;
b1 A
b10110010 C
1N
08
b1 <
0L
1P
1(
#644
0(
#646
0M
0"
b11 ;
1O
b10110010 D
b1 B
b10 <
b1010001 6
1(
#648
0(
#650
b1 1
b0 ;
0N
b11 <
0P
1(
#652
0(
#654
1M
1"
b1 ;
0O
b0 <
b1 2
1(
#656
0(
#658
b10100011 3
b10 ;
b10 A
b1100100 C
1N
b1 <
1P
1(
#660
0(
#662
0M
0"
b11 ;
1O
b1100100 D
b10 B
b10 <
b10100011 6
1(
#664
0(
#666
b10 1
b0 ;
0I
0N
b11 <
0P
1(
#668
0(
#670
1M
1"
1K
1&
17
b1 ;
0O
0'
0J
b0 <
b10 2
1(
#672
0(
#674
b1000110 3
b10 ;
b11 A
b11001001 C
1N
18
b1 <
1L
1P
1(
#676
0(
#678
0M
0"
b11 ;
1O
b11001001 D
b11 B
b10 <
b1000110 6
1(
#680
0(
#682
b11 1
b0 ;
1I
0N
b11 <
0P
1(
#684
0(
#686
1M
1"
0K
0&
07
b1 ;
0O
1'
1J
b0 <
b11 2
1(
#688
0(
#690
b10001101 3
b10 ;
b100 A
b10010010 C
1N
08
b1 <
0L
1P
1(
#692
0(
#694
0M
0"
b11 ;
1O
b10010010 D
b100 B
b10 <
b10001101 6
1(
#696
0(
#698
b100 1
b0 ;
0N
b11 <
0P
1(
#700
0(
#702
1M
1"
1K
1&
17
b1 ;
0O
b0 <
b100 2
1(
#704
0(
#706
b11011 3
b10 ;
b101 A
b100101 C
1N
18
b1 <
1L
1P
1(
#708
0(
#710
0M
0"
b11 ;
1O
b100101 D
b101 B
b10 <
b11011 6
1(
#712
0(
#714
b101 1
b0 ;
0I
0N
b11 <
0P
1(
#716
0(
#718
1M
1"
0K
0&
07
b1 ;
0O
0'
0J
b0 <
b101 2
1(
#720
0(
#722
b110110 3
b10 ;
b110 A
b1001010 C
1N
08
b1 <
0L
1P
1(
#724
0(
#726
0M
0"
b11 ;
1O
b1001010 D
b110 B
b10 <
b110110 6
1(
#728
0(
#730
b110 1
b0 ;
0N
b11 <
0P
1(
#732
0(
#734
1M
1"
b1 ;
0O
b0 <
b110 2
1(
#736
0(
#738
b1101100 3
b10 ;
b111 A
b10010100 C
1N
b1 <
1P
1(
#740
0(
#742
0M
0"
b11 ;
1O
b10010100 D
b111 B
b10 <
b1101100 6
1(
#744
0(
#746
b111 1
b0 ;
1I
0N
b11 <
0P
1(
#748
0(
#750
1M
1"
b1 ;
0O
1'
1J
b0 <
b111 2
1(
#752
0(
#754
b11011001 3
b10 ;
1E
b101000 G
b0 A
b11100001 C
1N
b1 <
1P
1(
#756
0(
#758
0M
0"
0E
b11101001 *
b11101001 ?
b101011 )
b101011 .
b11 ;
1O
b11100001 D
b101000 #
b101000 @
b101000 H
b0 B
1!
1F
b10 <
b11011001 6
1(
#760
0(
#762
19
b11011001 4
b0 =
b0 1
b0 ;
0N
b11 <
0P
0!
0F
1(
#764
0(
#766
b1 =
b101011 3
09
0O
1%
1:
b11011001 $
b11011001 /
b11011001 5
00
b0 >
b0 <
b0 2
1(
#768
0(
#770
b1 ;
0%
0:
10
b1 >
b101011 6
1(
#772
0(
#774
b10 =
b0 ;
b1 <
1(
#776
0(
#778
1M
1"
b1 ;
b10 >
b0 <
1(
#780
0(
#782
b1 A
b11000010 C
1N
b1010111 3
b10 ;
1P
b1 <
1(
#784
0(
#786
0M
0"
b11 ;
b10 <
b1010111 6
1O
b11000010 D
b1 B
1(
#788
0(
#790
0N
b1 1
b0 ;
0P
b11 <
1(
#792
0(
#794
1M
1"
b1 ;
b0 <
b1 2
0O
1(
#796
0(
#798
b10 A
b10000100 C
1N
b10101111 3
b10 ;
1P
b1 <
1(
#800
0(
#802
0M
0"
b11 ;
b10 <
b10101111 6
1O
b10000100 D
b10 B
1(
#804
0(
#806
0N
b10 1
b0 ;
0P
b11 <
1(
#808
0(
#810
1M
1"
1K
1&
17
b1 ;
b0 <
b10 2
0O
1(
#812
0(
#814
b11 A
b1001 C
1N
b1011111 3
b10 ;
1L
1P
18
b1 <
1(
#816
0(
#818
0M
0"
b11 ;
b10 <
b1011111 6
1O
b1001 D
b11 B
1(
#820
0(
#822
0I
0N
b11 1
b0 ;
0P
b11 <
1(
#824
0(
#826
1M
1"
0K
0&
07
b1 ;
b0 <
b11 2
0O
0'
0J
1(
#828
0(
#830
b100 A
b10010 C
1N
b10111110 3
b10 ;
0L
1P
08
b1 <
1(
#832
0(
#834
0M
0"
b11 ;
b10 <
b10111110 6
1O
b10010 D
b100 B
1(
#836
0(
#838
0N
b100 1
b0 ;
0P
b11 <
1(
#840
0(
#842
1M
1"
1K
1&
17
b1 ;
b0 <
b100 2
0O
1(
#844
0(
#846
b101 A
b100101 C
1N
b1111100 3
b10 ;
1L
1P
18
b1 <
1(
#848
0(
#850
0M
0"
b11 ;
b10 <
b1111100 6
1O
b100101 D
b101 B
1(
#852
0(
#854
0N
b101 1
b0 ;
0P
b11 <
1(
#856
0(
#858
1M
1"
0K
0&
07
b1 ;
b0 <
b101 2
0O
1(
#860
0(
#862
b110 A
b1001010 C
1N
b11111000 3
b10 ;
0L
1P
08
b1 <
1(
#864
0(
#866
0M
0"
b11 ;
b10 <
b11111000 6
1O
b1001010 D
b110 B
1(
#868
0(
#870
0N
b110 1
b0 ;
0P
b11 <
1(
#872
0(
#874
1M
1"
1K
1&
17
b1 ;
b0 <
b110 2
0O
1(
#876
0(
#878
b111 A
b10010101 C
1N
b11110000 3
b10 ;
1L
1P
18
b1 <
1(
#880
0(
#882
0M
0"
b11 ;
b10 <
b11110000 6
1O
b10010101 D
b111 B
1(
#884
0(
#886
1I
0N
b111 1
b0 ;
0P
b11 <
1(
#888
0(
#890
1M
1"
b1 ;
b0 <
b111 2
0O
1'
1J
1(
#892
0(
